<ExampleDefinition xmlns:xsd="http://www.w3.org/2001/XMLSchema" xmlns:xsi="http://www.w3.org/2001/XMLSchema-instance">
  <View>Examples/StyleAChart/UsePointMarkers.xaml</View>
  <ViewModel />
  <ImagePath>/SciChart.Examples;component/Resources/Images/ExampleImages/demoPointMarkers2.png</ImagePath>
  <IconPath>IconScatter</IconPath>
  <ToolTipDescription>Demonstrates the new PointMarker API in SciChart 2.0. Now built-in types handle Ellipse, Square, Cross, Triangle markers and a special type allows for UIElements to be rendered to bitmap at data-point values (SpriteMarker).</ToolTipDescription>
  <Description>
    Demonstrates the [url='http://support.scichart.com/index.php?/Knowledgebase/Article/View/17182/28/adding-data-pointmarkers']PointMarker API[/url] which allows data-point markers to be added to many RenderableSeries types.

    Now built-in types handle Ellipse, Square, Cross, Triangle, Inverted Triangle, X markers and a special type allows for UIElements to be rendered to bitmap at data-point values (SpriteMarker), so it's possible to render tens or hundreds of thousands of point-markers using this method.

    It is also possible to create custom PointMarkers by overriding BasePointMarker.InternalDraw using our RenderContext API.

    [b]Documentation Links[/b]

    - [url='http://support.scichart.com/index.php?/Knowledgebase/Article/View/17182/28/adding-data-pointmarkers']Data-Point Markers API[/url]
    - [url='http://www.scichart.com/documentation/v4.x/webframe.html#SciChart.Charting~SciChart.Charting.Visuals.PointMarkers_namespace.html']BasePointMarker Types[/url]     
  </Description>    
  <CodeFiles>
    <string>Resources/ExampleSourceFiles/StyleAChart/UsePointMarkers.xaml.txt</string>
    <string>Resources/ExampleSourceFiles/StyleAChart/UsePointMarkers.xaml.cs.txt</string>
    <string>Resources/ExampleSourceFiles/StyleAChart/UsePointMarkersResourceDictionary.xaml.txt</string>
  </CodeFiles>
  <Features>
    <Features>PointMarker</Features>
  </Features>
</ExampleDefinition>
